{
    "version": "0.2",
    "ignorePaths": [
        "content/acknowledgements.mdx",
        "package.json",
        "package-lock.json",
        "node_modules",
        "dist",
        "build",
        "out",
        "public",
        "package-lock.json",
        "package.json",
        "next.config.mjs",
        ".env",
        ".env.*",
        "cspell.json"
    ],
    "dictionaryDefinitions": [],
    "dictionaries": [],
    "words": [
        "Ahilleas",
        "Akzent",
        "analysed",
        "Anderes",
        "Ansichsein",
        "Assertoric",
        "atemporal",
        "aufheben",
        "Aufhebung",
        "ausgeglichen",
        "Autosize",
        "Befreiung",
        "Beschaffenheit",
        "Bestimmtheit",
        "Bestimmung",
        "Bluesky",
        "Burbidge",
        "Clientside",
        "clsx",
        "cockroachdb",
        "Collingwood",
        "couldn",
        "cuid",
        "Daseiendes",
        "Dasein",
        "defaultdb",
        "determinacies",
        "Diaception",
        "diremption",
        "distinguishedness",
        "Etwas",
        "Existenz",
        "fällt",
        "Filip",
        "Firgrep",
        "geltend",
        "Georg",
        "Geraets",
        "Guyer",
        "Hackett",
        "Halkyon",
        "headeronly",
        "Houlgate",
        "Identität",
        "IIFE",
        "Iluvatar",
        "Insichsein",
        "itselfness",
        "Keon",
        "lccn",
        "livemode",
        "lxviii",
        "macht",
        "mctaggart",
        "mdxeditor",
        "Meinen",
        "Mert",
        "mindmap",
        "Nicht",
        "Nichtsein",
        "Niklas",
        "nodownload",
        "numpages",
        "oppheve",
        "Overengineered",
        "ownness",
        "Parmenidean",
        "Pinkard",
        "posteriori",
        "posthog",
        "Prepyrus",
        "presuppositionless",
        "presuppositionlessness",
        "problematizes",
        "Purgatorio",
        "Realphilosophie",
        "reimagined",
        "Rokni",
        "Routledge",
        "Sache",
        "seiend",
        "seiende",
        "Seiendes",
        "Sein",
        "sich",
        "simpliciter",
        "SLQB",
        "spatio",
        "sphil",
        "squircle",
        "strikethrough",
        "subcontraries",
        "sublate",
        "sublated",
        "sublates",
        "sublating",
        "sublation",
        "Suchting",
        "SUPERADMIN",
        "systemphil",
        "Taggart",
        "tailwindcss",
        "tollere",
        "Trisokkas",
        "Übergang",
        "Unfreedom",
        "unmittelbare",
        "unseparated",
        "unseparatedness",
        "Upsert",
        "vanishedness",
        "Veränderung",
        "Verneinung",
        "webp",
        "Wissenschaft",
        "Yirmibes",
        "Zusätze"
    ],
    "enableFiletypes": [
        "mdx"
    ],
    "ignoreWords": [
        "biblatex",
        "datetime",
        "encyclopaedia",
        "msapplication",
        "nextra",
        "splitn"
    ],
    "flagWords": [
        "encyclopedia: encyclopaedia"
    ],
    "import": []
}
